mecoda_inat/__init__.py
mecoda_inat/mecoda_inat.py
mecoda_inat/models.py
mecoda_inat/py.typed
mecoda_inat/data/taxon_tree.csv
mecoda_inat-1.0.2.dist-info/LICENSE
mecoda_inat-1.0.2.dist-info/METADATA
mecoda_inat-1.0.2.dist-info/WHEEL
mecoda_inat-1.0.2.dist-info/top_level.txt
mecoda_inat-1.0.2.dist-info/RECORD
