Metadata-Version: 2.1
Name: mecoda-inat
Version: 1.0.2
Summary: Library to download information using INaturalist API.
Home-page: https://github.com/pynomaly/mecoda-inat
Author: Ana Alvarez
Author-email: ana.alvarez@icm.csic.es
License: GNU General Public License v3
Classifier: Development Status :: 4 - Beta
Classifier: Intended Audience :: Developers
Classifier: License :: OSI Approved :: GNU General Public License v3 or later (GPLv3+)
Classifier: Operating System :: Unix
Classifier: Operating System :: POSIX
Classifier: Programming Language :: Python
Classifier: Programming Language :: Python :: 3
Classifier: Programming Language :: Python :: 3.7
Classifier: Programming Language :: Python :: 3.8
Classifier: Programming Language :: Python :: 3.9
Classifier: Programming Language :: Python :: 3.11
Classifier: Topic :: Utilities
Classifier: Natural Language :: English
Requires-Python: >=3.6
License-File: LICENSE
Requires-Dist: pydantic
Requires-Dist: requests
Requires-Dist: pandas
